[
  {
    "createdAt": "2024-01-15T09:00:00Z",
    "detail": "新規プロジェクトの提案書をまとめる",
    "id": 1,
    "order": 1,
    "priority": "高",
    "status": "完了",
    "title": "プロジェクト提案書作成２"
  },
  {
    "createdAt": "2024-01-16T10:30:00Z",
    "detail": "週次定例会議に参加",
    "id": 2,
    "order": 2,
    "priority": "中",
    "status": "完了",
    "title": "チームミーティング"
  },
  {
    "createdAt": "2024-01-14T14:20:00Z",
    "detail": "APIドキュメントの最新版に更新",
    "id": 3,
    "order": 3,
    "priority": "低",
    "status": "完了",
    "title": "ドキュメント更新"
  },
  {
    "createdAt": "2025-11-23T09:16:08.130Z",
    "detail": "テスト",
    "id": 1763889368130,
    "priority": "低",
    "status": "完了",
    "title": "テスト"
  },
  {
    "createdAt": "2024-01-17T08:00:00Z",
    "detail": "顧客要件のヒアリングを実施",
    "id": 4,
    "order": 4,
    "priority": "高",
    "status": "完了",
    "title": "顧客ヒアリング"
  },
  {
    "createdAt": "2024-01-18T11:30:00Z",
    "detail": "システムのバックアップを取得",
    "id": 5,
    "order": 5,
    "priority": "中",
    "status": "完了",
    "title": "システムバックアップ"
  },
  {
    "createdAt": "2024-01-19T15:45:00Z",
    "detail": "テストケースの設計と作成",
    "id": 6,
    "order": 6,
    "priority": "高",
    "status": "完了",
    "title": "テストケース設計"
  },
  {
    "createdAt": "2024-01-20T09:30:00Z",
    "detail": "バグ修正と改善案の検討",
    "id": 7,
    "order": 7,
    "priority": "中",
    "status": "完了",
    "title": "バグ修正"
  },
  {
    "createdAt": "2024-01-21T13:00:00Z",
    "detail": "プレゼン資料の作成と修正",
    "id": 8,
    "order": 8,
    "priority": "高",
    "status": "完了",
    "title": "プレゼン資料作成"
  },
  {
    "createdAt": "2024-01-22T10:15:00Z",
    "detail": "チームメンバーへのトレーニング実施",
    "id": 9,
    "order": 9,
    "priority": "低",
    "status": "完了",
    "title": "トレーニング実施"
  },
  {
    "createdAt": "2024-01-23T14:30:00Z",
    "detail": "サーバーのメンテナンスと確認",
    "id": 10,
    "order": 10,
    "priority": "高",
    "status": "完了",
    "title": "サーバーメンテナンス"
  },
  {
    "createdAt": "2024-01-24T08:45:00Z",
    "detail": "顧客報告書の作成と提出",
    "id": 11,
    "order": 11,
    "priority": "中",
    "status": "完了",
    "title": "顧客報告書"
  },
  {
    "createdAt": "2024-01-25T11:20:00Z",
    "detail": "新機能の仕様書を確認",
    "id": 12,
    "order": 12,
    "priority": "低",
    "status": "完了",
    "title": "仕様書確認"
  },
  {
    "createdAt": "2024-01-26T09:00:00Z",
    "detail": "パフォーマンスの最適化を検討",
    "id": 13,
    "order": 13,
    "priority": "高",
    "status": "完了",
    "title": "パフォーマンス最適化"
  },
  {
    "createdAt": "2024-01-27T15:30:00Z",
    "detail": "セキュリティ対応の実施",
    "id": 14,
    "order": 14,
    "priority": "高",
    "status": "完了",
    "title": "セキュリティ対応"
  },
  {
    "createdAt": "2024-01-28T10:00:00Z",
    "detail": "デザインレビューの実施",
    "id": 15,
    "order": 15,
    "priority": "中",
    "status": "完了",
    "title": "デザインレビュー"
  },
  {
    "createdAt": "2024-01-29T13:45:00Z",
    "detail": "ユーザーテストの準備と実施",
    "id": 16,
    "order": 16,
    "priority": "中",
    "status": "完了",
    "title": "ユーザーテスト"
  },
  {
    "createdAt": "2024-01-30T08:30:00Z",
    "detail": "リリース前の最終確認",
    "id": 17,
    "order": 17,
    "priority": "高",
    "status": "完了",
    "title": "リリース前確認"
  },
  {
    "createdAt": "2024-01-31T12:00:00Z",
    "detail": "メールマーケティングキャンペーンの設定",
    "id": 18,
    "order": 18,
    "priority": "低",
    "status": "完了",
    "title": "メールキャンペーン"
  },
  {
    "createdAt": "2024-02-01T09:30:00Z",
    "detail": "データベース最適化とインデックス作成",
    "id": 19,
    "order": 19,
    "priority": "中",
    "status": "完了",
    "title": "DB最適化"
  },
  {
    "createdAt": "2024-02-02T14:15:00Z",
    "detail": "ログ分析とエラー調査",
    "id": 20,
    "order": 20,
    "priority": "高",
    "status": "完了",
    "title": "ログ分析"
  }
]